README.md
setup.cfg
setup.py
distributions/Binomialdistribution.py
distributions/Gaussiandistribution.py
distributions/Generaldistribution.py
distributions/__init__.py
methanol_15.egg-info/PKG-INFO
methanol_15.egg-info/SOURCES.txt
methanol_15.egg-info/dependency_links.txt
methanol_15.egg-info/not-zip-safe
methanol_15.egg-info/top_level.txt